yun/Yun.py
yun/__init__.py
yun_ir-1.0.dist-info/LICENSE
yun_ir-1.0.dist-info/METADATA
yun_ir-1.0.dist-info/WHEEL
yun_ir-1.0.dist-info/top_level.txt
yun_ir-1.0.dist-info/RECORD
