Metadata-Version: 2.1
Name: yun-ir
Version: 1.0
Summary: A Python client for Yun.ir URL shortener API
Home-page: https://github.com/ALIILAPRO/yun-ir
Author: ALIILAPRO
Author-email: aliilapro@pm.me
License: MIT
Platform: UNKNOWN
Classifier: Development Status :: 3 - Alpha
Classifier: Intended Audience :: Developers
Classifier: License :: OSI Approved :: MIT License
Classifier: Programming Language :: Python :: 3.7
Classifier: Programming Language :: Python :: 3.8
Classifier: Programming Language :: Python :: 3.9
Classifier: Programming Language :: Python :: 3.10
Requires-Dist: requests
